ingredient_slicer/__init__.py
ingredient_slicer/_constants.py
ingredient_slicer/_ingredient_slicer.py
ingredient_slicer/_regex_patterns.py
ingredient_slicer/_utils.py
ingredient_slicer/models/__init__.py
ingredient_slicer/models/parsed_ingredient_data.py
ingredient_slicer/models/quantity_unit_data.py
ingredient_slicer/parenthesis/__init__.py
ingredient_slicer/parenthesis/equivalence_parenthesis_strategy.py
ingredient_slicer/parenthesis/parenthesis_handler.py
ingredient_slicer/parenthesis/quantity_only_parenthesis_strategy.py
ingredient_slicer/parenthesis/quantity_unit_only_parenthesis_strategy.py
ingredient_slicer/parser/__init__.py
ingredient_slicer/parser/ingredient_parser.py
ingredient_slicer/standardizer/__init__.py
ingredient_slicer/standardizer/_ingredient_standardizer.py
ingredient_slicer/standardizer/_ingredient_standardizer_builder.py
ingredient_slicer-1.2.2.dist-info/licenses/LICENSE
ingredient_slicer-1.2.2.dist-info/METADATA
ingredient_slicer-1.2.2.dist-info/WHEEL
ingredient_slicer-1.2.2.dist-info/top_level.txt
ingredient_slicer-1.2.2.dist-info/RECORD
