Metadata-Version: 2.4
Name: ingredient_slicer
Version: 1.2.2
Summary: Parses unstructured recipe ingredient text into standardized quantities, units, and foods
Author-email: Angus Watters <anguswatters@gmail.com>
License: MIT License
Keywords: ingredient,parser,recipe,text processing,food,cooking,grocery,shopping
Classifier: Development Status :: 3 - Alpha
Classifier: Intended Audience :: Developers
Classifier: License :: OSI Approved :: MIT License
Classifier: Operating System :: Microsoft :: Windows
Classifier: Operating System :: Unix
Classifier: Programming Language :: Python :: 3.9
Classifier: Programming Language :: Python :: 3.10
Classifier: Programming Language :: Python :: 3.11
Classifier: Topic :: Utilities
Requires-Python: >=3.7
License-File: LICENSE
Provides-Extra: test
Requires-Dist: pytest; extra == "test"
Requires-Dist: pip-tools; extra == "test"
Provides-Extra: dev
Requires-Dist: black; extra == "dev"
Dynamic: license-file
